README.md
setup.py
Panis.egg-info/PKG-INFO
Panis.egg-info/SOURCES.txt
Panis.egg-info/dependency_links.txt
Panis.egg-info/requires.txt
Panis.egg-info/top_level.txt
panis/__init__.py
panis/__main__.py
panis/about.py
panis/farm.py
panis/table.py
panis/bakery/__init__.py
panis/bakery/allocation.py
panis/bakery/allocation_report.py
panis/bakery/allocation_report_save.py
panis/bakery/batch.py
panis/bakery/dough.py
panis/bakery/parameter.py
panis/bakery/process.py
panis/bakery/product.py
panis/bakery/recipe.py
panis/bakery/shape.py
panis/cooperation/__init__.py
panis/cooperation/meetingsubject.py
panis/cooperation/meetingsubjectlog.py
panis/gui/__init__.py
panis/gui/bakery/__init__.py
panis/gui/bakery/allocation.py
panis/gui/bakery/batch.py
panis/gui/bakery/parameter.py
panis/gui/bakery/product.py
panis/gui/bakery/recipe.py
panis/gui/bakery/shape.py
panis/gui/cooperation/__init__.py
panis/gui/cooperation/meetingsubject.py
panis/gui/logistic/__init__.py
panis/gui/logistic/goods.py
panis/gui/sales/__init__.py
panis/gui/sales/client.py
panis/gui/sales/delivery.py
panis/gui/sales/distribution.py
panis/gui/sales/order.py
panis/gui/sales/order2.py
panis/gui/widget/__init__.py
panis/gui/widget/comboboxdict.py
panis/gui/widget/scrollbarframe.py
panis/gui/widget/test_fixed_header.py
panis/gui/widget/valueentry.py
panis/logistic/__init__.py
panis/logistic/goods.py
panis/logistic/stock.py
panis/report/__init__.py
panis/report/latex_report.py
panis/sales/__init__.py
panis/sales/client.py
panis/sales/delivery.py
panis/sales/distribution.py
panis/sales/order.py
panis/sales/order_report.py
panis/sales/product.py
tests/test_lhf.py